processos/tb_me.vhd
-- +++++++++++++++++++++++++++++++++++++++++++++++++++++++++++++++++++++++
-- UFPR, BCC, ci210                       autor: Roberto Hexsel, 27out2015
--                                               rev 12set2016
-- +++++++++++++++++++++++++++++++++++++++++++++++++++++++++++++++++++++++


--++++++++++++++++++++++++++++++++++++++++++++++++++++++++++++++++++++++++
-- esqueleto do testbench para ME que detecta ...01111110...
--++++++++++++++++++++++++++++++++++++++++++++++++++++++++++++++++++++++++
use work.p_wires.all;

entity tb_ME is
end tb_ME;


architecture TB of tb_ME is


  type test_record is record
                        e : bit;        -- entrada
                        s : bit;        -- saida esperada
  end record;
  type test_array is array(positive range <>) of test_record;
    
  constant test_vectors : test_array := (
    -- entr, saida
    ('0', '0'),
    ('0', '0'),
    ('1', '0'),
    ('1', '0'),
    ('1', '0'),
    ('1', '0'),
    ('1', '0'),
    ('1', '0'),
    ('0', '0'),
    ('1', '1'),
    ('1', '0'),
    ('1', '0'),
    ('1', '0'),
    ('1', '0'),
    ('1', '0'),      -- acrescente mais testes a partir daqui
    ('0', '0'),      
    ('1', '0'),      
    ('1', '0'),      
    ('1', '0'),      
    ('1', '0'),
    ('1', '0'),
    ('1', '0'),
    ('0', '0'),
    ('0', '1'),
    ('1', '0'),
    ('1', '0'),
    ('1', '0'),
    ('1', '0'),
    ('1', '0'),
    ('1', '0'),
    ('1', '0'),
    ('0', '0'),
    ('0', '0'),
    ('1', '0'),
    ('0', '0'),
    ('1', '0'),
    ('0', '0'),
    ('1', '0'),
    ('0', '0'),
    ('1', '0'),
    ('0', '0'),
    ('1', '0'),
    ('0', '0'),
    ('1', '0'),
    ('1', '0'),
    ('1', '0'),
    ('1', '0'),
    ('1', '0'),
    ('0', '0'),
    ('0', '0'),
    ('1', '0'),
    ('1', '0'),
    ('1', '0'),
    ('1', '0'),
    ('1', '0'),
    ('1', '0'),
    ('0', '0'),
    ('0', '1'),
    ('0', '0'),
    ('1', '0'),
    ('1', '0'),
    ('1', '0'),
    ('1', '0'),
    ('1', '0'),
    ('1', '0'),
    ('0', '0'),
    ('0', '1'),
    ('0', '0'),
    ('1', '0'),
    ('1', '0'),
    ('1', '0'),
    ('1', '0'),
    ('1', '0'),
    ('1', '0'),
    ('0', '0'),
    ('0', '1'),
    ('0', '0')

);
  -- tipo enumerado: A=0, B=1, C=2, ...
  -- acrescente tantos estados quanto necessario
  type states is (A, B, C, D, E, F, G, H, I);

  signal curr_st, next_st : states;

  signal clk, reset, entr, found, esperada : bit;

  signal dbg_st : integer;
  
begin  -- TB

  dbg_st <= integer(states'pos(curr_st));  -- debugging only

  U_state_reg: process(reset, clk)
  begin
    if reset = '0' then
      curr_st <= A;
    elsif rising_edge(clk) then
      curr_st <= next_st;
    end if;
  end process U_state_reg;

  U_st_transitions: process(curr_st, entr)
  begin                  -- Máquina de Moore
    case curr_st is
      when A =>
        if entr = '0' then next_st <= B; 
        else next_st <= A;       end if;
        found <= '0';

      when B =>
        if entr = '1' then next_st <= C;
        else next_st <= B;       end if;
        found <= '0';

      when C =>
        if entr = '1' then next_st <= D;
        else next_st <= B;       end if;
        found <= '0';	

      when D =>
        if entr = '1' then next_st <= E;
	else next_st <= B;	end if;
	found <= '0';

      when E =>
      	if entr = '1' then next_st <= F;  
 	else next_st <= B;	end if;   
	found <= '0';

      when F =>
  	if entr = '1' then next_st <= G;
  	else next_st <= B;	end if;
	found <= '0';

      when G =>
   	if entr = '1' then next_st <= H;   
   	else next_st <= B;	end if;
	found <= '0';

      when H =>
  	if entr = '0' then next_st <= I;
  	else next_st <= A;	end if; 
 	found <= '0';

      when I =>
  	if entr = '0' then next_st <= B;
  	else next_st <= A;	end if;
	found <= '1';


    end case;
  end process U_st_transitions;
  -- ----------------------------------------------------------------
  

  -- ----------------------------------------------------------------
  U_testValues: process -- test the circuit
    variable v : test_record;
  begin

    esperada <= '0';
    entr     <= '0';

    wait until rising_edge(clk);        -- espera por dois ciclos e então 
    wait until rising_edge(clk);        --  inicia os testes
    
    for j in test_vectors'range loop

      v := test_vectors(j);
      entr     <= v.e;
      esperada <= v.s;

      assert esperada = found
        report LF & "entr="& B2STR(entr) & " esp=" & B2STR(esperada) &
               " found=" & B2STR(found) & " estado=" & natural'image(dbg_st)
        severity note;

      wait until rising_edge(clk);
      
    end loop;

    wait; -- -------------- end the simulation ------------------------
    
  end process;

  
  U_clock: process      -- concurrent process for clock, clock runs free
  begin
    clk <= '0';
    wait for t_clock_period / 2;
    clk <= '1';
    wait for t_clock_period / 2;
  end process;

  U_reset: process      -- reset initializes all
  begin
    reset <= '0';
    wait for t_reset;
    reset <= '1';	-- end of reset pulse
    wait;               -- this process stops here
  end process;
  
end TB;

----------------------------------------------------------------
configuration CFG_TB of TB_ME is
	for TB
        end for;
end CFG_TB;
----------------------------------------------------------------

processos/v_me.vcd
$date
  Tue Oct  1 14:32:01 2019
$end
$version
  GHDL v0
$end
$timescale
  1 fs
$end
$scope module standard $end
$upscope $end
$scope module std_logic_1164 $end
$upscope $end
$scope module numeric_std $end
$upscope $end
$scope module p_wires $end
$upscope $end
$scope module tb_me $end
$comment curr_st is not handled $end
$comment next_st is not handled $end
$var reg 1 ! clk $end
$var reg 1 " reset $end
$var reg 1 # entr $end
$var reg 1 $ found $end
$var reg 1 % esperada $end
$var integer 32 & dbg_st $end
$upscope $end
$enddefinitions $end
#0
0!
0"
0#
0$
0%
b0 &
#500000
1!
#750000
1"
#1000000
0!
#1500000
1!
b1 &
#2000000
0!
#2500000
1!
#3000000
0!
#3500000
1!
1#
#4000000
0!
#4500000
1!
b10 &
#5000000
0!
#5500000
1!
b11 &
#6000000
0!
#6500000
1!
b100 &
#7000000
0!
#7500000
1!
b101 &
#8000000
0!
#8500000
1!
b110 &
#9000000
0!
#9500000
1!
0#
b111 &
#10000000
0!
#10500000
1!
1#
1$
1%
b1000 &
#11000000
0!
#11500000
1!
0$
0%
b0 &
#12000000
0!
#12500000
1!
#13000000
0!
#13500000
1!
#14000000
0!
#14500000
1!
#15000000
0!
#15500000
1!
#16000000
0!
#16500000
1!
0#
#17000000
0!
#17500000
1!
1#
b1 &
#18000000
0!
#18500000
1!
b10 &
#19000000
0!
#19500000
1!
b11 &
#20000000
0!
#20500000
1!
b100 &
#21000000
0!
#21500000
1!
b101 &
#22000000
0!
#22500000
1!
b110 &
#23000000
0!
#23500000
1!
0#
b111 &
#24000000
0!
#24500000
1!
1$
1%
b1000 &
#25000000
0!
#25500000
1!
1#
0$
0%
b1 &
#26000000
0!
#26500000
1!
b10 &
#27000000
0!
#27500000
1!
b11 &
#28000000
0!
#28500000
1!
b100 &
#29000000
0!
#29500000
1!
b101 &
#30000000
0!
#30500000
1!
b110 &
#31000000
0!
#31500000
1!
b111 &
#32000000
0!
#32500000
1!
0#
b0 &
#33000000
0!
#33500000
1!
b1 &
#34000000
0!
#34500000
1!
1#
#35000000
0!
#35500000
1!
0#
b10 &
#36000000
0!
#36500000
1!
1#
b1 &
#37000000
0!
#37500000
1!
0#
b10 &
#38000000
0!
#38500000
1!
1#
b1 &
#39000000
0!
#39500000
1!
0#
b10 &
#40000000
0!
#40500000
1!
1#
b1 &
#41000000
0!
#41500000
1!
0#
b10 &
#42000000
0!
#42500000
1!
1#
b1 &
#43000000
0!
#43500000
1!
0#
b10 &
#44000000
0!
#44500000
1!
1#
b1 &
#45000000
0!
#45500000
1!
b10 &
#46000000
0!
#46500000
1!
b11 &
#47000000
0!
#47500000
1!
b100 &
#48000000
0!
#48500000
1!
b101 &
#49000000
0!
#49500000
1!
0#
b110 &
#50000000
0!
#50500000
1!
b1 &
#51000000
0!
#51500000
1!
1#
#52000000
0!
#52500000
1!
b10 &
#53000000
0!
#53500000
1!
b11 &
#54000000
0!
#54500000
1!
b100 &
#55000000
0!
#55500000
1!
b101 &
#56000000
0!
#56500000
1!
b110 &
#57000000
0!
#57500000
1!
0#
b111 &
#58000000
0!
#58500000
1!
1$
1%
b1000 &
#59000000
0!
#59500000
1!
0$
0%
b1 &
#60000000
0!
#60500000
1!
1#
#61000000
0!
#61500000
1!
b10 &
#62000000
0!
#62500000
1!
b11 &
#63000000
0!
#63500000
1!
b100 &
#64000000
0!
#64500000
1!
b101 &
#65000000
0!
#65500000
1!
b110 &
#66000000
0!
#66500000
1!
0#
b111 &
#67000000
0!
#67500000
1!
1$
1%
b1000 &
#68000000
0!
#68500000
1!
0$
0%
b1 &
#69000000
0!
#69500000
1!
1#
#70000000
0!
#70500000
1!
b10 &
#71000000
0!
#71500000
1!
b11 &
#72000000
0!
#72500000
1!
b100 &
#73000000
0!
#73500000
1!
b101 &
#74000000
0!
#74500000
1!
b110 &
#75000000
0!
#75500000
1!
0#
b111 &
#76000000
0!
#76500000
1!
1$
1%
b1000 &
#77000000
0!
#77500000
1!
0$
0%
b1 &
